datascibox/__init__.py
datascibox/generators.py
datascibox/itertools_recipes.py
datascibox/pandas_utilities.py
datascibox-0.0.1.dist-info/LICENSE.md
datascibox-0.0.1.dist-info/METADATA
datascibox-0.0.1.dist-info/WHEEL
datascibox-0.0.1.dist-info/top_level.txt
datascibox-0.0.1.dist-info/RECORD
